VibeBot/__init__.py
VibeBot/__main__.py
VibeBot/__version__.py
VibeBot/bot.py
VibeBot/server.py
VibeBot/utils/__init__.py
VibeBot/utils/io.py
VibeBot-1.0.1.dist-info/AUTHORS.md
VibeBot-1.0.1.dist-info/LICENSE
VibeBot-1.0.1.dist-info/METADATA
VibeBot-1.0.1.dist-info/WHEEL
VibeBot-1.0.1.dist-info/top_level.txt
VibeBot-1.0.1.dist-info/RECORD
